openserv/__init__.py
openserv/agent.py
openserv/capability.py
openserv/client.py
openserv/config.py
openserv/exceptions.py
openserv/logger.py
openserv/server.py
openserv/types.py
openserv_sdk-0.1.0.dist-info/METADATA
openserv_sdk-0.1.0.dist-info/WHEEL
openserv_sdk-0.1.0.dist-info/licenses/LICENSE
openserv_sdk-0.1.0.dist-info/RECORD
