Metadata-Version: 2.4
Name: openserv-sdk
Version: 0.1.0
Summary: OpenServ SDK for building AI agents with advanced cognitive capabilities
Project-URL: Homepage, https://openserv.ai
Project-URL: Repository, https://github.com/openserv-labs/python-sdk
Project-URL: Documentation, https://docs.openserv.ai
Author-email: OpenServ Labs <info@openserv.ai>
License: MIT
License-File: LICENSE
Keywords: agents,ai,openserv,sdk
Requires-Python: >=3.8
Requires-Dist: aiohttp>=3.8.0
Requires-Dist: bcrypt>=4.0.1
Requires-Dist: cryptography>=41.0.0
Requires-Dist: fastapi>=0.104.0
Requires-Dist: httpx>=0.25.0
Requires-Dist: openai>=1.3.0
Requires-Dist: pydantic>=2.4.2
Requires-Dist: python-dotenv>=1.0.0
Requires-Dist: python-jose>=3.3.0
Requires-Dist: python-multipart>=0.0.6
Requires-Dist: requests>=2.31.0
Requires-Dist: starlette>=0.27.0
Requires-Dist: uvicorn>=0.24.0
Provides-Extra: test
Requires-Dist: black>=23.0.0; extra == 'test'
Requires-Dist: flake8>=6.0.0; extra == 'test'
Requires-Dist: mypy>=1.0.0; extra == 'test'
Requires-Dist: pytest-asyncio>=0.25.0; extra == 'test'
Requires-Dist: pytest-cov>=4.0.0; extra == 'test'
Requires-Dist: pytest>=7.0.0; extra == 'test'
